{
  "animateLoading": true,
  "borderRadius": "{{appsmith.theme.borderRadius.appBorderRadius}}",
  "bottomRow": 13,
  "displayName": "Text",
  "dynamicBindingPathList": [
    {
      "key": "fontFamily"
    },
    {
      "key": "borderRadius"
    },
    {
      "key": "text"
    }
  ],
  "dynamicHeight": "FIXED",
  "dynamicTriggerPathList": [],
  "fontFamily": "{{appsmith.theme.fontFamily.appFont}}",
  "fontSize": "1.875rem",
  "fontStyle": "BOLD",
  "hideCard": false,
  "iconSVG": "/static/media/icon.97c59b523e6f70ba6f40a10fc2c7c5b5.svg",
  "isDeprecated": false,
  "isLoading": false,
  "isVisible": true,
  "key": "s8ew0jemrb",
  "leftColumn": 2,
  "maxDynamicHeight": 9000,
  "minDynamicHeight": 4,
  "overflow": "NONE",
  "parentColumnSpace": 4.234375,
  "parentId": "9cskg5v2ka",
  "parentRowSpace": 10,
  "renderMode": "CANVAS",
  "rightColumn": 62,
  "searchTags": [
    "typography",
    "paragraph",
    "label"
  ],
  "shouldTruncate": false,
  "text": "{{utils.dashboardMetrics.data.totalOrderValue}}",
  "textAlign": "LEFT",
  "textColor": "#fafafa",
  "topRow": 9,
  "truncateButtonColor": "#FFC13D",
  "type": "TEXT_WIDGET",
  "version": 1,
  "widgetId": "dxxlga6bxt",
  "widgetName": "txt_miniSidebarValue"
}