{
  "accentColor": "{{appsmith.theme.colors.primaryColor}}",
  "animateLoading": true,
  "borderColor": "#E0DEDE",
  "borderRadius": "{{appsmith.theme.borderRadius.appBorderRadius}}",
  "borderWidth": "1",
  "bottomRow": 54,
  "boxShadow": "{{appsmith.theme.boxShadow.appBoxShadow}}",
  "canFreezeColumn": true,
  "childStylesheet": {
    "button": {
      "borderRadius": "{{appsmith.theme.borderRadius.appBorderRadius}}",
      "boxShadow": "none",
      "buttonColor": "{{appsmith.theme.colors.primaryColor}}"
    },
    "editActions": {
      "discardBorderRadius": "{{appsmith.theme.borderRadius.appBorderRadius}}",
      "discardButtonColor": "{{appsmith.theme.colors.primaryColor}}",
      "saveBorderRadius": "{{appsmith.theme.borderRadius.appBorderRadius}}",
      "saveButtonColor": "{{appsmith.theme.colors.primaryColor}}"
    },
    "iconButton": {
      "borderRadius": "{{appsmith.theme.borderRadius.appBorderRadius}}",
      "boxShadow": "none",
      "buttonColor": "{{appsmith.theme.colors.primaryColor}}"
    },
    "menuButton": {
      "borderRadius": "{{appsmith.theme.borderRadius.appBorderRadius}}",
      "boxShadow": "none",
      "menuColor": "{{appsmith.theme.colors.primaryColor}}"
    }
  },
  "columnOrder": [
    "Order",
    "Product",
    "Category",
    "Amount"
  ],
  "columnUpdatedAt": 1682327314960,
  "columnWidthMap": {
    "Amount": 122,
    "Description": 340,
    "Product": 149,
    "ShippedQuantity": 177,
    "status": 85,
    "step": 70,
    "task": 245
  },
  "compactMode": "TALL",
  "defaultPageSize": 0,
  "defaultSelectedRowIndex": "-1",
  "defaultSelectedRowIndices": [
    0
  ],
  "delimiter": ",",
  "displayName": "Table",
  "dynamicBindingPathList": [
    {
      "key": "accentColor"
    },
    {
      "key": "borderRadius"
    },
    {
      "key": "boxShadow"
    },
    {
      "key": "tableData"
    },
    {
      "key": "primaryColumns.Order.computedValue"
    },
    {
      "key": "primaryColumns.Product.computedValue"
    },
    {
      "key": "primaryColumns.Category.computedValue"
    },
    {
      "key": "primaryColumns.Amount.computedValue"
    }
  ],
  "dynamicPropertyPathList": [
    {
      "key": "tableData"
    }
  ],
  "dynamicTriggerPathList": [],
  "enableClientSideSearch": true,
  "enableServerSideFiltering": false,
  "hideCard": false,
  "horizontalAlignment": "LEFT",
  "iconSVG": "/static/media/icon.db8a9cbd2acd22a31ea91cc37ea2a46c.svg",
  "inlineEditingSaveOption": "ROW_LEVEL",
  "isDeprecated": false,
  "isLoading": false,
  "isSortable": false,
  "isVisible": true,
  "isVisibleDownload": false,
  "isVisibleFilters": false,
  "isVisiblePagination": false,
  "isVisibleSearch": false,
  "key": "dkwhcauuu7",
  "label": "Data",
  "leftColumn": 1,
  "minWidth": 450,
  "needsHeightForContent": true,
  "parentColumnSpace": 16.375,
  "parentId": "e13haxrlld",
  "parentRowSpace": 10,
  "primaryColumns": {
    "Amount": {
      "alias": "Amount",
      "allowCellWrapping": false,
      "allowSameOptionsInNewRow": true,
      "cellBackground": "",
      "columnType": "text",
      "computedValue": "{{(() => { const tableData = tbl_product.processedTableData || []; return tableData.length > 0 ? tableData.map((currentRow, currentIndex) => ( currentRow[\"Amount\"])) :  currentRow[\"Amount\"] })()}}",
      "enableFilter": true,
      "enableSort": true,
      "fontStyle": "",
      "horizontalAlignment": "LEFT",
      "id": "Amount",
      "index": 2,
      "isCellEditable": false,
      "isCellVisible": true,
      "isDerived": false,
      "isDisabled": false,
      "isDiscardVisible": true,
      "isEditable": false,
      "isSaveVisible": true,
      "isVisible": true,
      "label": "Amount",
      "originalId": "Amount",
      "sticky": "",
      "textColor": "",
      "textSize": "0.875rem",
      "validation": {},
      "verticalAlignment": "CENTER",
      "width": 150
    },
    "Category": {
      "alias": "Category",
      "allowCellWrapping": false,
      "allowSameOptionsInNewRow": true,
      "cellBackground": "",
      "columnType": "text",
      "computedValue": "{{(() => { const tableData = tbl_product.processedTableData || []; return tableData.length > 0 ? tableData.map((currentRow, currentIndex) => ( currentRow[\"Category\"])) :  currentRow[\"Category\"] })()}}",
      "enableFilter": true,
      "enableSort": true,
      "fontStyle": "",
      "horizontalAlignment": "LEFT",
      "id": "Category",
      "index": 1,
      "isCellEditable": false,
      "isCellVisible": true,
      "isDerived": false,
      "isDisabled": false,
      "isDiscardVisible": true,
      "isEditable": false,
      "isSaveVisible": true,
      "isVisible": true,
      "label": "Category",
      "originalId": "Category",
      "sticky": "",
      "textColor": "",
      "textSize": "0.875rem",
      "validation": {},
      "verticalAlignment": "CENTER",
      "width": 150
    },
    "Order": {
      "alias": "Order",
      "allowCellWrapping": false,
      "columnType": "number",
      "computedValue": "{{(() => { const tableData = tbl_product.processedTableData || []; return tableData.length > 0 ? tableData.map((currentRow, currentIndex) => ( currentRow[\"Order\"])) :  currentRow[\"Order\"] })()}}",
      "enableFilter": true,
      "enableSort": true,
      "horizontalAlignment": "LEFT",
      "id": "Order",
      "index": 4,
      "isCellEditable": false,
      "isCellVisible": true,
      "isDerived": false,
      "isDisabled": false,
      "isDiscardVisible": true,
      "isEditable": false,
      "isSaveVisible": true,
      "isVisible": false,
      "label": "Order#",
      "originalId": "Order",
      "sticky": "",
      "textSize": "0.875rem",
      "validation": {},
      "verticalAlignment": "CENTER",
      "width": 150
    },
    "Product": {
      "alias": "Product",
      "allowCellWrapping": false,
      "allowSameOptionsInNewRow": true,
      "cellBackground": "",
      "columnType": "text",
      "computedValue": "{{(() => { const tableData = tbl_product.processedTableData || []; return tableData.length > 0 ? tableData.map((currentRow, currentIndex) => ( currentRow[\"Product\"])) :  currentRow[\"Product\"] })()}}",
      "enableFilter": true,
      "enableSort": true,
      "fontStyle": "",
      "horizontalAlignment": "LEFT",
      "id": "Product",
      "index": 0,
      "isCellEditable": false,
      "isCellVisible": true,
      "isDerived": false,
      "isDisabled": false,
      "isDiscardVisible": true,
      "isEditable": false,
      "isSaveVisible": true,
      "isVisible": true,
      "label": "Product",
      "originalId": "Product",
      "sticky": "",
      "textColor": "",
      "textSize": "0.875rem",
      "validation": {},
      "verticalAlignment": "CENTER",
      "width": 150
    }
  },
  "renderMode": "CANVAS",
  "responsiveBehavior": "fill",
  "rightColumn": 62,
  "searchKey": "",
  "serverSidePaginationEnabled": false,
  "tableData": "{{\n\t[\n\t{\n\t\tProduct: tbl_returns.selectedRow.Product,\n\t\tCategory: tbl_returns.selectedRow.Description,\n\t\tAmount: tbl_returns.selectedRow.Amount,\n\t\tOrder: 1,\n\t}\n]\n}}",
  "textSize": "0.875rem",
  "topRow": 43,
  "totalRecordsCount": "0",
  "type": "TABLE_WIDGET_V2",
  "version": 1,
  "verticalAlignment": "CENTER",
  "widgetId": "lpt99et358",
  "widgetName": "tbl_product"
}